hack4you/__init__.py
hack4you/courses.py
hack4you/utils.py
santis1986_hack4you-0.1.0.dist-info/METADATA
santis1986_hack4you-0.1.0.dist-info/WHEEL
santis1986_hack4you-0.1.0.dist-info/top_level.txt
santis1986_hack4you-0.1.0.dist-info/RECORD
