Metadata-Version: 2.4
Name: santis1986-hack4you
Version: 0.1.0
Summary: Una biblioteca para consultar cursos de hack4you.
Home-page: https://hack4u.io
Author: Marcelo Vazquez
Dynamic: author
Dynamic: description-content-type
Dynamic: home-page
Dynamic: summary
